vdf/__init__.py
vdf/_io.c
vdf/_io.cpython-39-darwin.so
vdf/exceptions.py
vdf/io.py
vdf/vdf_dict.py
vdf3-3.1.1.1.dist-info/LICENSE
vdf3-3.1.1.1.dist-info/METADATA
vdf3-3.1.1.1.dist-info/WHEEL
vdf3-3.1.1.1.dist-info/top_level.txt
vdf3-3.1.1.1.dist-info/RECORD
