Metadata-Version: 2.1
Name: vdf3
Version: 3.1.1.1
Summary: Library for working with Valve's VDF text format
Home-page: https://github.com/Gobot1234/vdf3
Author: Gobot1234
License: MIT
Download-URL: https://github.com/Gobot1234/vdf3/archive/3.1.1.1.tar.gz
Project-URL: Code, https://github.com/Gobot1234/vdf3
Project-URL: Issue tracker, https://github.com/Gobot1234/vdf3/issues
Keywords: valve keyvalue vdf tf2 dota2 csgo
Platform: UNKNOWN
Classifier: Development Status :: 5 - Production/Stable
Classifier: Intended Audience :: Developers
Classifier: License :: OSI Approved :: MIT License
Classifier: Topic :: Software Development :: Libraries :: Python Modules
Classifier: Natural Language :: English
Classifier: Operating System :: OS Independent
Classifier: Programming Language :: Python :: 3 :: Only
Classifier: Programming Language :: Python :: 3.7
Classifier: Programming Language :: Python :: 3.8
Classifier: Programming Language :: Python :: 3.9
Classifier: Topic :: Software Development :: Libraries
Classifier: Topic :: Software Development :: Libraries :: Python Modules
Classifier: Typing :: Typed
Requires: multidict
Requires-Python: >=3.7.0
